{
    "name": "Creamy Blue v2",
    "description": "thanks lol",
    "version": "2.0.0",
    "spec": "2",
    "authors": [
        {
            "name": "mcnf",
            "id": "915696300803096596"
        }
    ],
    "semanticColors": {
        "CHAT_BACKGROUND": ["#6382b9"],
        "HEADER_PRIMARY": ["#6382b9"],
        "HEADER_SECONDARY": ["#6382b9"],
        "TEXT_NORMAL": ["#6382b9"],
        "TEXT_MUTED": ["#6382b9"],
        "INTERACTIVE_NORMAL": ["#6382b9"],
        "INTERACTIVE_HOVER": ["#6382b9"],
        "INTERACTIVE_ACTIVE": ["#6382b9"],
        "INTERACTIVE_MUTED": ["#6382b9"],
        "BACKGROUND_PRIMARY": ["#6382b9"],
        "CARD_PRIMARY_BG": ["#6382b9"],
        "BG_BASE_PRIMARY": ["#6382b9"],
        "BACKGROUND_SECONDARY": ["#6382b9"],
        "CARD_SECONDARY_BG": ["#6382b9"],
        "BG_BASE_SECONDARY": ["#6382b9"],
        "BACKGROUND_SECONDARY_ALT": ["#6382b9"],
        "BACKGROUND_TERTIARY": ["#6382b9"],
        "BG_BASE_TERTIARY": ["#6382b9"],
        "BACKGROUND_ACCENT": ["#6382b9"],
        "BACKGROUND_MOBILE_PRIMARY": ["#6382b9"],
        "BACKGROUND_MOBILE_SECONDARY": ["#6382b9"],
        "BACKGROUND_NESTED_FLOATING": ["#6382b9"],
        "BACKGROUND_MESSAGE_HOVER": ["#6382b9"],
        "BACKGROUND_MODIFIER_HOVER": ["#6382b9"],
        "BACKGROUND_MODIFIER_ACTIVE": ["#6382b9"],
        "BACKGROUND_MODIFIER_SELECTED": ["#6382b9"],
        "BACKGROUND_MODIFIER_ACCENT": ["#6382b9"],
        "BACKGROUND_MENTIONED": ["#6382b9"],
        "BACKGROUND_MENTIONED_HOVER": ["#6382b9"],
        "CHANNELTEXTAREA_BACKGROUND": ["#6382b9"],
        "REDESIGN_ACTIVITY_CARD_BACKGROUND": ["#6382b9"],
        "REDESIGN_BUTTON_SECONDARY_BACKGROUND": ["#6382b9"],
        "REDESIGN_BUTTON_SECONDARY_BORDER": ["#6382b9"],
        "REDESIGN_CHANNEL_CATEGORY_NAME_TEXT": ["#6382b9"],
        "REDESIGN_CHANNEL_NAME_TEXT": ["#6382b9"],
        "REDESIGN_CHAT_INPUT_BACKGROUND": ["#6382b9"],
        "REDESIGN_BUTTON_TERTIARY_BACKGROUND": ["#6382b9"],
        "CHANNELS_DEFAULT": ["#6382b9"],
        "CHANNEL_ICON": ["#6382b9"],
        "TEXT_PRIMARY": ["#6382b9"],
        "TEXT_LINK": ["#6382b9"],
        "THREAD_CHANNEL_SPINE": ["#6382b9"],
        "BG_MOD_FAINT": ["#6382b9"],
        "EMBED_BACKGROUND": ["#6382b9"],
        "INPUT_BACKGROUND": ["#6382b9"]
    },
    "rawColors": {
        "PRIMARY_100": "#6382b9",
        "PRIMARY_200": "#6382b9",
        "PRIMARY_300": "#6382b9",
        "PRIMARY_330": "#6382b9",
        "PRIMARY_360": "#6382b9",
        "PRIMARY_400": "#6382b9",
        "PRIMARY_460": "#6382b9",
        "PRIMARY_500": "#6382b9",
        "PRIMARY_530": "#6382b9",
        "PRIMARY_600": "#6382b9",
        "PRIMARY_630": "#6382b9",
        "PRIMARY_645": "#6382b9",
        "PRIMARY_660": "#6382b9",
        "PRIMARY_700": "#6382b9",
        "PRIMARY_800": "#6382b9",
        "PLUM_10": "#6382b9",
        "PLUM_15": "#6382b9",
        "PLUM_16": "#6382b9",
        "PLUM_17": "#6382b9",
        "PLUM_18": "#6382b9",
        "PLUM_20": "#6382b9",
        "PLUM_3": "#6382b9",
        "PLUM_4": "#6382b9",
        "PLUM_6": "#6382b9",
        "BRAND_260": "#6382b9",
        "BRAND_300": "#6382b9",
        "BRAND_330": "#6382b9",
        "BRAND_345": "#6382b9",
        "BRAND_360": "#6382b9",
        "BRAND_400": "#6382b9",
        "BRAND_430": "#6382b9",
        "BRAND_460": "#6382b9",
        "BRAND_500": "#6382b9",
        "BRAND_530": "#6382b9",
        "BRAND_560": "#6382b9",
        "BRAND_600": "#6382b9",
        "BRAND_630": "#6382b9",
        "BRAND_660": "#6382b9",
        "BRAND_700": "#6382b9",
        "RED_260": "#6382b9",
        "RED_300": "#6382b9",
        "RED_330": "#6382b9",
        "RED_345": "#6382b9",
        "RED_360": "#6382b9",
        "RED_400": "#6382b9",
        "RED_430": "#6382b9",
        "RED_460": "#6382b9",
        "RED_500": "#6382b9",
        "RED_530": "#6382b9",
        "RED_560": "#6382b9",
        "RED_600": "#6382b9",
        "RED_630": "#6382b9",
        "RED_660": "#6382b9",
        "RED_700": "#6382b9",
        "ROLE_DEFAULT": "#6382b9",
        "ORANGE_260": "#6382b9",
        "ORANGE_300": "#6382b9",
        "ORANGE_330": "#6382b9",
        "ORANGE_345": "#6382b9",
        "ORANGE_360": "#6382b9",
        "ORANGE_400": "#6382b9",
        "ORANGE_430": "#6382b9",
        "ORANGE_460": "#6382b9",
        "ORANGE_500": "#6382b9",
        "ORANGE_530": "#6382b9",
        "ORANGE_560": "#6382b9",
        "ORANGE_600": "#6382b9",
        "ORANGE_630": "#6382b9",
        "ORANGE_660": "#6382b9",
        "ORANGE_700": "#6382b9",
        "YELLOW_260": "#6382b9",
        "YELLOW_300": "#6382b9",
        "YELLOW_330": "#6382b9",
        "YELLOW_345": "#6382b9",
        "YELLOW_360": "#6382b9",
        "YELLOW_400": "#6382b9",
        "YELLOW_430": "#6382b9",
        "YELLOW_460": "#6382b9",
        "YELLOW_500": "#6382b9",
        "YELLOW_530": "#6382b9",
        "YELLOW_560": "#6382b9",
        "YELLOW_600": "#6382b9",
        "YELLOW_630": "#6382b9",
        "YELLOW_660": "#6382b9",
        "YELLOW_700": "#6382b9",
        "GREEN_260": "#6382b9",
        "GREEN_300": "#6382b9",
        "GREEN_330": "#6382b9",
        "GREEN_345": "#6382b9",
        "GREEN_360": "#6382b9",
        "GREEN_400": "#6382b9",
        "GREEN_430": "#6382b9",
        "GREEN_460": "#6382b9",
        "GREEN_500": "#6382b9",
        "GREEN_530": "#6382b9",
        "GREEN_560": "#6382b9",
        "GREEN_600": "#6382b9",
        "GREEN_630": "#6382b9",
        "GREEN_660": "#6382b9",
        "GREEN_700": "#6382b9",
        "BLUE_260": "#6382b9",
        "BLUE_300": "#6382b9",
        "BLUE_330": "#6382b9",
        "BLUE_345": "#6382b9",
        "BLUE_360": "#6382b9",
        "BLUE_400": "#6382b9",
        "BLUE_430": "#6382b9",
        "BLUE_460": "#6382b9",
        "BLUE_500": "#6382b9",
        "BLUE_530": "#6382b9",
        "BLUE_560": "#6382b9",
        "BLUE_600": "#6382b9",
        "BLUE_630": "#6382b9",
        "BLUE_660": "#6382b9",
        "BLUE_700": "#6382b9",
        "WHITE_500": "#6382b9",
        "WHITE_630": "#6382b9"
    },
    "background": {
        "blur": 0.1,
        "url": ""
    },
    "plus": {
        "version": "0",
        "iconpack": "solar",
        "mentionLineColor": "#6382b9",
        "customOverlays": true,
        "icons": {
            "ic_radio_circle_checked": "#6382b9",
            "ic_radio_circle_checked__overlay": "#6382b9",
            "ic_radio_square_24px": "#6382b9",
            "ic_radio_square_checked_24px": "#6382b9",
            "ic_radio_square_checked_24px__overlay": "#6382b9",
            "ic_selection_checked_24px": "#6382b9",
            "ic_selection_checked_24px__overlay": "#6382b9",
            "img_guild_folder": "#6382b9"
        }
    },
    "fonts": {
        "ABCGintoNord-ExtraBold": "https://github.com/Rairof/Theme-Fonts/blob/main/Linotte/Linotte-Bold.ttf?raw=1",
        "ggsans-Bold": "https://github.com/Rairof/Theme-Fonts/blob/main/Linotte/Linotte-Bold.ttf?raw=1",
        "ggsans-BoldItalic": "https://github.com/Rairof/Theme-Fonts/blob/main/Linotte/Linotte-Bold.ttf?raw=1",
        "ggsans-ExtraBold": "https://github.com/Rairof/Theme-Fonts/blob/main/Linotte/Linotte-Bold.ttf?raw=1",
        "ggsans-ExtraBoldItalic": "https://github.com/Rairof/Theme-Fonts/blob/main/Linotte/Linotte-Bold.ttf?raw=1",
        "ggsans-Medium": "https://github.com/Rairof/Theme-Fonts/blob/main/Linotte/Linotte-SemiBold.ttf?raw=1",
        "ggsans-MediumItalic": "https://github.com/Rairof/Theme-Fonts/blob/main/Linotte/Linotte-SemiBold.ttf?raw=1",
        "ggsans-Normal": "https://github.com/Rairof/Theme-Fonts/blob/main/Linotte/Linotte-Regular.ttf?raw=1",
        "ggsans-NormalItalic": "https://github.com/Rairof/Theme-Fonts/blob/main/Linotte/Linotte-RegularItalic.ttf?raw=1",
        "ggsans-Semibold": "https://github.com/Rairof/Theme-Fonts/blob/main/Linotte/Linotte-SemiBold.ttf?raw=1",
        "ggsans-SemiboldItalic": "https://github.com/Rairof/Theme-Fonts/blob/main/Linotte/Linotte-SemiBold.ttf?raw=1",
        "NotoSans-Bold": "https://github.com/Rairof/Theme-Fonts/blob/main/Linotte/Linotte-Bold.ttf?raw=1",
        "NotoSans-ExtraBold": "https://github.com/Rairof/Theme-Fonts/blob/main/Linotte/Linotte-Bold.ttf?raw=1",
        "NotoSans-Medium": "https://github.com/Rairof/Theme-Fonts/blob/main/Linotte/Linotte-SemiBold.ttf?raw=1",
        "NotoSans-Normal": "https://github.com/Rairof/Theme-Fonts/blob/main/Linotte/Linotte-Regular.ttf?raw=1",
        "NotoSans-NormalItalic": "https://github.com/Rairof/Theme-Fonts/blob/main/Linotte/Linotte-RegularItalic.ttf?raw=1",
        "NotoSans-Semibold": "https://github.com/Rairof/Theme-Fonts/blob/main/Linotte/Linotte-SemiBold.ttf?raw=1",
        "SourceCodePro-Semibold": "https://github.com/Rairof/Theme-Fonts/blob/main/Linotte/Linotte-SemiBold.ttf?raw=1"
    }
}
